{
	"pages": [ //pages数组中第一项表示应用启动页，参考：https://uniapp.dcloud.io/collocation/pages
		{
            "path" : "pages/login/login",
            "style" : {
				"navigationBarTitleText": "极致生活"
			}
        },{
			"path": "pages/index/index",
			"style": {
				"navigationBarTitleText": "极致生活"
			}
		}
        ,{
            "path" : "pages/index/exchangeIdentity/exchangeIdentity",
            "style" : {
				"navigationBarTitleText": "切换身份"
			}
        }
        ,{
            "path" : "pages/index/lookResult/lookResult",
            "style" : {
				"navigationBarTitleText": "业绩查询"
			}
        }
        ,{
            "path" : "pages/technician/technician",
            "style" : {
				"navigationBarTitleText": "极致生活-技术员端"
			}
        }
        ,{
            "path" : "pages/technician/waitingDo/waitingDo",
            "style" : {
				"navigationBarTitleText": "订单详情"
			}
        },
		{
            "path" : "pages/technician/waitingDo/working",
            "style" : {
				"navigationBarTitleText": "订单详情"
			}
        }
        ,{
            "path" : "pages/technician/working/working",
            "style" : {
				"navigationBarTitleText": "处理中"
			}
        }
        ,{
            "path" : "pages/technician/fillMoney/fillMoney",
            "style" : {
				"navigationBarTitleText": "补款中"
			}
        }
        ,{
            "path" : "pages/technician/done/done",
            "style" : {
				"navigationBarTitleText": "处理完成"
			}
        }
    ],
	"globalStyle": {
		"navigationBarTextStyle": "black",
		"navigationBarTitleText": "极致生活",
		"navigationBarBackgroundColor": "#F8F8F8",
		"backgroundColor": "#000"
	}
}
